Workbook
Name Hist_Data: Table1[#All]

Sheet Historical_Data
A1: Date | B1: Units_Sold | C1: Price_per_Unit | D1: Revenue | E1: Fixed_Cost | F1: Variable_Cost
A2: 45292 | B2: 800 | C2: 1200 | D2: 960000 | E2: 250000 | F2: 192000
A3: 45293 | B3: 812 | C3: 1200 | D3: 974400 | E3: 250020 | F3: 194880
A4: 45294 | B4: 795 | C4: 1201 | D4: 954795 | E4: 250040 | F4: 190959
A5: 45295 | B5: 830 | C5: 1201 | D5: 996830 | E5: 250060 | F5: 199366
A6: 45296 | B6: 845 | C6: 1202 | D6: 1015690 | E6: 250080 | F6: 203138
A7: 45297 | B7: 820 | C7: 1202 | D7: 985640 | E7: 250100 | F7: 197128
A8: 45298 | B8: 860 | C8: 1203 | D8: 1034580 | E8: 250120 | F8: 206916
A9: 45299 | B9: 875 | C9: 1203 | D9: 1052625 | E9: 250140 | F9: 210525
A10: 45300 | B10: 890 | C10: 1204 | D10: 1071560 | E10: 250160 | F10: 214312
A11: 45301 | B11: 905 | C11: 1204 | D11: 1089620 | E11: 250180 | F11: 217924
A12: 45302 | B12: 920 | C12: 1205 | D12: 1108600 | E12: 250200 | F12: 221720
A13: 45303 | B13: 935 | C13: 1205 | D13: 1126675 | E13: 250220 | F13: 225335
... A122: 45412 | B122: 2195 | C122: 1247 | D122: 2737165 | E122: 251900 | F122: 547433

Sheet Assumptions
A1: Variable | B1: Value
A2: Price Growth | B2: 0.03
A3: Inflation | B3: 0.05
A4: Variable Cost % | B4: 0.2
A5: Tax Rate | B5: 0.25
A6: Forecast Months | B6: 1
A7: Units_Growth | B7: 0.1

Sheet Income_statement
A1: Forecasted Income Statement
A3: Total Revenue | B3: =SUM(Revenue_and_expense_forecast!D:D) -> 85337413
A5: Total Cost | B5: =SUM(Revenue_and_expense_forecast!E:G) -> 49892124
A7: EBITDA | B7: =B3-B5 -> 35445289
A9: Tax | B9: =B7*Assumptions!B5 -> 8861322.2
A11: Net Profit | B11: =B7-B9 -> 26583967
A13: EBITDA Margin | B13: =B7/B3 -> 0.41535462
A15: NET PROFIT MARGIN | B15: =B11/B3 -> 0.31151597

Sheet SUMMARY
D1: SUMMARY
C3: Row Labels | D3: Sum of Revenue Forecast | E3: Sum of Total_Cost_Forecast | F3: Sum of Net profit Forecast
C4: 45413 | D4: 2738139.9 | E4: 799667.47 | F4: 1938472.5
C5: 45414 | D5: 2739115.2 | E5: 800002.11 | F5: 1939113.1
C6: 45415 | D6: 2740090.9 | E6: 800336.92 | F6: 1939754
C7: 45416 | D7: 2741066.9 | E7: 800671.9 | F7: 1940395
C8: 45417 | D8: 2742043.2 | E8: 801007.04 | F8: 1941036.1
C9: 45418 | D9: 2743019.9 | E9: 801342.36 | F9: 1941677.5
C10: 45419 | D10: 2743996.9 | E10: 801677.85 | F10: 1942319
C11: 45420 | D11: 2744974.3 | E11: 802013.5 | F11: 1942960.8
C12: 45421 | D12: 2745952 | E12: 802349.33 | F12: 1943602.7
C13: 45422 | D13: 2746930.1 | E13: 802685.32 | F13: 1944244.7
C14: 45423 | D14: 2747908.5 | E14: 803021.49 | F14: 1944887
C15: 45424 | D15: 2748887.3 | E15: 803357.82 | F15: 1945529.4
... C34: 45443 | D34: 2767550.2 | E34: 809780.61 | F34: 1957769.6
C35: Grand Total | D35: 85337413 | E35: 24946062 | F35: 60391351

Sheet Revenue_and_expense_forecast
A1: Date | B1: Units_Forecast | C1: Price_Forecast | D1: Revenue Forecast | E1: Fixed_Cost_forecast | F1: Variable_Cost_forecast | G1: Total_Cost_Forecast | H1: Net profit Forecast
A2: =MAX(Historical_Data!A:A)+1 -> 45413 | B2: {=INDEX(Historical_Data!B:B,COUNTA(Historical_Data!B:B))*(1+Assumptions!$B$7/365)} -> 2195.6014 | C2: {=INDEX(Historical_Data!C:C,COUNTA(Historical_Data!C:C))*(1+Assumptions!$B$2/365)} -> 1247.1025 | D2: =B2*C2 -> 2738139.9 | E2: {=INDEX(Historical_Data!E:E,COUNTA(Historical_Data!E:E))*(1+Assumptions!B3/365)} -> 251934.51 | F2: {=INDEX(Historical_Data!F:F,COUNTA(Historical_Data!F:F))*(1+Assumptions!$B$4/365)} -> 547732.96 | G2: =E2+F2 -> 799667.47 | H2: =D2-G2 -> 1938472.5
A3: =A2+1 -> 45414 | B3: =B2*(1+Assumptions!$B$7/365) -> 2196.2029 | C3: =C2*(1+Assumptions!$B$2/365) -> 1247.205 | D3: =B3*C3 -> 2739115.2 | E3: =E2*(1+Assumptions!$B$3/365) -> 251969.02 | F3: =F2*(1+Assumptions!$B$4/365) -> 548033.09 | G3: =E3+F3 -> 800002.11 | H3: =D3-G3 -> 1939113.1
A4: =A3+1 -> 45415 | B4: =B3*(1+Assumptions!$B$7/365) -> 2196.8046 | C4: =C3*(1+Assumptions!$B$2/365) -> 1247.3075 | D4: =B4*C4 -> 2740090.9 | E4: =E3*(1+Assumptions!$B$3/365) -> 252003.53 | F4: =F3*(1+Assumptions!$B$4/365) -> 548333.38 | G4: =E4+F4 -> 800336.92 | H4: =D4-G4 -> 1939754
A5: =A4+1 -> 45416 | B5: =B4*(1+Assumptions!$B$7/365) -> 2197.4065 | C5: =C4*(1+Assumptions!$B$2/365) -> 1247.41 | D5: =B5*C5 -> 2741066.9 | E5: =E4*(1+Assumptions!$B$3/365) -> 252038.06 | F5: =F4*(1+Assumptions!$B$4/365) -> 548633.84 | G5: =E5+F5 -> 800671.9 | H5: =D5-G5 -> 1940395
A6: =A5+1 -> 45417 | B6: =B5*(1+Assumptions!$B$7/365) -> 2198.0085 | C6: =C5*(1+Assumptions!$B$2/365) -> 1247.5126 | D6: =B6*C6 -> 2742043.2 | E6: =E5*(1+Assumptions!$B$3/365) -> 252072.58 | F6: =F5*(1+Assumptions!$B$4/365) -> 548934.46 | G6: =E6+F6 -> 801007.04 | H6: =D6-G6 -> 1941036.1
A7: =A6+1 -> 45418 | B7: =B6*(1+Assumptions!$B$7/365) -> 2198.6107 | C7: =C6*(1+Assumptions!$B$2/365) -> 1247.6151 | D7: =B7*C7 -> 2743019.9 | E7: =E6*(1+Assumptions!$B$3/365) -> 252107.11 | F7: =F6*(1+Assumptions!$B$4/365) -> 549235.25 | G7: =E7+F7 -> 801342.36 | H7: =D7-G7 -> 1941677.5
A8: =A7+1 -> 45419 | B8: =B7*(1+Assumptions!$B$7/365) -> 2199.2131 | C8: =C7*(1+Assumptions!$B$2/365) -> 1247.7176 | D8: =B8*C8 -> 2743996.9 | E8: =E7*(1+Assumptions!$B$3/365) -> 252141.65 | F8: =F7*(1+Assumptions!$B$4/365) -> 549536.2 | G8: =E8+F8 -> 801677.85 | H8: =D8-G8 -> 1942319
A9: =A8+1 -> 45420 | B9: =B8*(1+Assumptions!$B$7/365) -> 2199.8156 | C9: =C8*(1+Assumptions!$B$2/365) -> 1247.8202 | D9: =B9*C9 -> 2744974.3 | E9: =E8*(1+Assumptions!$B$3/365) -> 252176.19 | F9: =F8*(1+Assumptions!$B$4/365) -> 549837.31 | G9: =E9+F9 -> 802013.5 | H9: =D9-G9 -> 1942960.8
A10: =A9+1 -> 45421 | B10: =B9*(1+Assumptions!$B$7/365) -> 2200.4183 | C10: =C9*(1+Assumptions!$B$2/365) -> 1247.9227 | D10: =B10*C10 -> 2745952 | E10: =E9*(1+Assumptions!$B$3/365) -> 252210.73 | F10: =F9*(1+Assumptions!$B$4/365) -> 550138.59 | G10: =E10+F10 -> 802349.33 | H10: =D10-G10 -> 1943602.7
A11: =A10+1 -> 45422 | B11: =B10*(1+Assumptions!$B$7/365) -> 2201.0211 | C11: =C10*(1+Assumptions!$B$2/365) -> 1248.0253 | D11: =B11*C11 -> 2746930.1 | E11: =E10*(1+Assumptions!$B$3/365) -> 252245.28 | F11: =F10*(1+Assumptions!$B$4/365) -> 550440.04 | G11: =E11+F11 -> 802685.32 | H11: =D11-G11 -> 1944244.7
A12: =A11+1 -> 45423 | B12: =B11*(1+Assumptions!$B$7/365) -> 2201.6241 | C12: =C11*(1+Assumptions!$B$2/365) -> 1248.1279 | D12: =B12*C12 -> 2747908.5 | E12: =E11*(1+Assumptions!$B$3/365) -> 252279.84 | F12: =F11*(1+Assumptions!$B$4/365) -> 550741.65 | G12: =E12+F12 -> 803021.49 | H12: =D12-G12 -> 1944887
A13: =A12+1 -> 45424 | B13: =B12*(1+Assumptions!$B$7/365) -> 2202.2273 | C13: =C12*(1+Assumptions!$B$2/365) -> 1248.2305 | D13: =B13*C13 -> 2748887.3 | E13: =E12*(1+Assumptions!$B$3/365) -> 252314.39 | F13: =F12*(1+Assumptions!$B$4/365) -> 551043.43 | G13: =E13+F13 -> 803357.82 | H13: =D13-G13 -> 1945529.4
A14: =A13+1 -> 45425 | B14: =B13*(1+Assumptions!$B$7/365) -> 2202.8307 | C14: =C13*(1+Assumptions!$B$2/365) -> 1248.3331 | D14: =B14*C14 -> 2749866.4 | E14: =E13*(1+Assumptions!$B$3/365) -> 252348.96 | F14: =F13*(1+Assumptions!$B$4/365) -> 551345.37 | G14: =E14+F14 -> 803694.33 | H14: =D14-G14 -> 1946172
... A32: =A31+1 -> 45443 | B32: =B31*(1+Assumptions!$B$7/365) -> 2213.7193 | C32: =C31*(1+Assumptions!$B$2/365) -> 1250.1812 | D32: =B32*C32 -> 2767550.2 | E32: =E31*(1+Assumptions!$B$3/365) -> 252971.91 | F32: =F31*(1+Assumptions!$B$4/365) -> 556808.7 | G32: =E32+F32 -> 809780.61 | H32: =D32-G32 -> 1957769.6

Sheet Dashboard
